{
  "program_name": "sample_ibumad_6",
  "verification_ns": 223414,
  "kernel_compiler": "clang",
  "call_tree": [
    {
      "file": "kernel/bpf/verifier.c:19995:19995",
      "inclusive_ns": 956,
      "exclusive_ns": 956,
      "function": "bpf_check_btf_info_early"
    },
    {
      "file": "kernel/bpf/verifier.c:19999:19999",
      "inclusive_ns": 406,
      "exclusive_ns": 406,
      "function": "add_subprog_and_kfunc"
    },
    {
      "file": "kernel/bpf/verifier.c:20003:20003",
      "inclusive_ns": 318,
      "exclusive_ns": 318,
      "function": "check_subprogs"
    },
    {
      "file": "kernel/bpf/verifier.c:20007:20007",
      "inclusive_ns": 3505,
      "exclusive_ns": 3505,
      "function": "bpf_check_btf_info"
    },
    {
      "file": "kernel/bpf/verifier.c:20011:20011",
      "inclusive_ns": 5064,
      "exclusive_ns": 5064,
      "function": "check_and_resolve_insns"
    },
    {
      "file": "kernel/bpf/verifier.c:20015:20015",
      "inclusive_ns": 150,
      "exclusive_ns": 150,
      "function": "bpf_prog_is_offloaded"
    },
    {
      "file": "kernel/bpf/verifier.c:20021:20021",
      "inclusive_ns": 2817,
      "exclusive_ns": 2817,
      "function": "bpf_check_cfg"
    },
    {
      "file": "kernel/bpf/verifier.c:20025:20025",
      "inclusive_ns": 2619,
      "exclusive_ns": 2619,
      "function": "bpf_compute_postorder"
    },
    {
      "file": "kernel/bpf/verifier.c:20029:20029",
      "inclusive_ns": 1467,
      "exclusive_ns": 1467,
      "function": "bpf_stack_liveness_init"
    },
    {
      "file": "kernel/bpf/verifier.c:20033:20033",
      "inclusive_ns": 153,
      "exclusive_ns": 153,
      "function": "check_attach_btf_id"
    },
    {
      "file": "kernel/bpf/verifier.c:20037:20037",
      "inclusive_ns": 5045,
      "exclusive_ns": 5045,
      "function": "bpf_compute_const_regs"
    },
    {
      "file": "kernel/bpf/verifier.c:20041:20041",
      "inclusive_ns": 304,
      "exclusive_ns": 304,
      "function": "bpf_prune_dead_branches"
    },
    {
      "file": "kernel/bpf/verifier.c:20045:20045",
      "inclusive_ns": 1957,
      "exclusive_ns": 1957,
      "function": "sort_subprogs_topo"
    },
    {
      "file": "kernel/bpf/verifier.c:20049:20049",
      "inclusive_ns": 5546,
      "exclusive_ns": 5546,
      "function": "bpf_compute_scc"
    },
    {
      "file": "kernel/bpf/verifier.c:20053:20053",
      "inclusive_ns": 112742,
      "exclusive_ns": 107829,
      "function": "bpf_compute_live_registers",
      "children": [
        {
          "file": "kernel/bpf/liveness.c:2159:2159",
          "inclusive_ns": 155,
          "exclusive_ns": 155,
          "function": "compute_insn_live_regs",
          "arg": 0
        },
        {
          "file": "kernel/bpf/liveness.c:2159:2159",
          "inclusive_ns": 185,
          "exclusive_ns": 185,
          "function": "compute_insn_live_regs",
          "arg": 1
        },
        {
          "file": "kernel/bpf/liveness.c:2159:2159",
          "inclusive_ns": 177,
          "exclusive_ns": 177,
          "function": "compute_insn_live_regs",
          "arg": 2
        },
        {
          "file": "kernel/bpf/liveness.c:2159:2159",
          "inclusive_ns": 175,
          "exclusive_ns": 175,
          "function": "compute_insn_live_regs",
          "arg": 3
        },
        {
          "file": "kernel/bpf/liveness.c:2159:2159",
          "inclusive_ns": 162,
          "exclusive_ns": 162,
          "function": "compute_insn_live_regs",
          "arg": 4
        },
        {
          "file": "kernel/bpf/liveness.c:2159:2159",
          "inclusive_ns": 152,
          "exclusive_ns": 152,
          "function": "compute_insn_live_regs",
          "arg": 5
        },
        {
          "file": "kernel/bpf/liveness.c:2159:2159",
          "inclusive_ns": 161,
          "exclusive_ns": 161,
          "function": "compute_insn_live_regs",
          "arg": 6
        },
        {
          "file": "kernel/bpf/liveness.c:2159:2159",
          "inclusive_ns": 162,
          "exclusive_ns": 162,
          "function": "compute_insn_live_regs",
          "arg": 7
        },
        {
          "file": "kernel/bpf/liveness.c:2159:2159",
          "inclusive_ns": 233,
          "exclusive_ns": 233,
          "function": "compute_insn_live_regs",
          "arg": 8
        },
        {
          "file": "kernel/bpf/liveness.c:2159:2159",
          "inclusive_ns": 175,
          "exclusive_ns": 175,
          "function": "compute_insn_live_regs",
          "arg": 9
        },
        {
          "file": "kernel/bpf/liveness.c:2159:2159",
          "inclusive_ns": 162,
          "exclusive_ns": 162,
          "function": "compute_insn_live_regs",
          "arg": 10
        },
        {
          "file": "kernel/bpf/liveness.c:2159:2159",
          "inclusive_ns": 151,
          "exclusive_ns": 151,
          "function": "compute_insn_live_regs",
          "arg": 11
        },
        {
          "file": "kernel/bpf/liveness.c:2159:2159",
          "inclusive_ns": 162,
          "exclusive_ns": 162,
          "function": "compute_insn_live_regs",
          "arg": 12
        },
        {
          "file": "kernel/bpf/liveness.c:2159:2159",
          "inclusive_ns": 151,
          "exclusive_ns": 151,
          "function": "compute_insn_live_regs",
          "arg": 13
        },
        {
          "file": "kernel/bpf/liveness.c:2159:2159",
          "inclusive_ns": 162,
          "exclusive_ns": 162,
          "function": "compute_insn_live_regs",
          "arg": 14
        },
        {
          "file": "kernel/bpf/liveness.c:2159:2159",
          "inclusive_ns": 165,
          "exclusive_ns": 165,
          "function": "compute_insn_live_regs",
          "arg": 15
        },
        {
          "file": "kernel/bpf/liveness.c:2159:2159",
          "inclusive_ns": 163,
          "exclusive_ns": 163,
          "function": "compute_insn_live_regs",
          "arg": 16
        },
        {
          "file": "kernel/bpf/liveness.c:2159:2159",
          "inclusive_ns": 161,
          "exclusive_ns": 161,
          "function": "compute_insn_live_regs",
          "arg": 17
        },
        {
          "file": "kernel/bpf/liveness.c:2159:2159",
          "inclusive_ns": 210,
          "exclusive_ns": 210,
          "function": "compute_insn_live_regs",
          "arg": 18
        },
        {
          "file": "kernel/bpf/liveness.c:2159:2159",
          "inclusive_ns": 163,
          "exclusive_ns": 163,
          "function": "compute_insn_live_regs",
          "arg": 19
        },
        {
          "file": "kernel/bpf/liveness.c:2159:2159",
          "inclusive_ns": 162,
          "exclusive_ns": 162,
          "function": "compute_insn_live_regs",
          "arg": 20
        },
        {
          "file": "kernel/bpf/liveness.c:2159:2159",
          "inclusive_ns": 162,
          "exclusive_ns": 162,
          "function": "compute_insn_live_regs",
          "arg": 21
        },
        {
          "file": "kernel/bpf/liveness.c:2159:2159",
          "inclusive_ns": 202,
          "exclusive_ns": 202,
          "function": "compute_insn_live_regs",
          "arg": 22
        },
        {
          "file": "kernel/bpf/liveness.c:2159:2159",
          "inclusive_ns": 166,
          "exclusive_ns": 166,
          "function": "compute_insn_live_regs",
          "arg": 23
        },
        {
          "file": "kernel/bpf/liveness.c:2159:2159",
          "inclusive_ns": 171,
          "exclusive_ns": 171,
          "function": "compute_insn_live_regs",
          "arg": 24
        },
        {
          "file": "kernel/bpf/liveness.c:2159:2159",
          "inclusive_ns": 151,
          "exclusive_ns": 151,
          "function": "compute_insn_live_regs",
          "arg": 25
        },
        {
          "file": "kernel/bpf/liveness.c:2159:2159",
          "inclusive_ns": 171,
          "exclusive_ns": 171,
          "function": "compute_insn_live_regs",
          "arg": 26
        },
        {
          "file": "kernel/bpf/liveness.c:2159:2159",
          "inclusive_ns": 163,
          "exclusive_ns": 163,
          "function": "compute_insn_live_regs",
          "arg": 27
        },
        {
          "file": "kernel/bpf/liveness.c:2159:2159",
          "inclusive_ns": 178,
          "exclusive_ns": 178,
          "function": "compute_insn_live_regs",
          "arg": 28
        }
      ]
    },
    {
      "file": "kernel/bpf/verifier.c:20057:20057",
      "inclusive_ns": 323,
      "exclusive_ns": 323,
      "function": "mark_fastcall_patterns"
    },
    {
      "file": "kernel/bpf/verifier.c:20061:20061",
      "inclusive_ns": 35113,
      "exclusive_ns": 35113,
      "function": "do_check_main"
    },
    {
      "file": "kernel/bpf/verifier.c:20062:20062",
      "inclusive_ns": 162,
      "exclusive_ns": 162,
      "function": "do_check_subprogs"
    },
    {
      "file": "kernel/bpf/verifier.c:20064:20064",
      "inclusive_ns": 150,
      "exclusive_ns": 150,
      "function": "bpf_prog_is_offloaded"
    },
    {
      "file": "kernel/bpf/verifier.c:20074:20074",
      "inclusive_ns": 237,
      "exclusive_ns": 237,
      "function": "bpf_remove_fastcall_spills_fill"
    },
    {
      "file": "kernel/bpf/verifier.c:20077:20077",
      "inclusive_ns": 1052,
      "exclusive_ns": 1052,
      "function": "check_max_stack_depth"
    },
    {
      "file": "kernel/bpf/verifier.c:20081:20081",
      "inclusive_ns": 254,
      "exclusive_ns": 254,
      "function": "bpf_optimize_bpf_loop"
    },
    {
      "file": "kernel/bpf/verifier.c:20085:20085",
      "inclusive_ns": 254,
      "exclusive_ns": 254,
      "function": "bpf_opt_hard_wire_dead_code_bra"
    },
    {
      "file": "kernel/bpf/verifier.c:20087:20087",
      "inclusive_ns": 197,
      "exclusive_ns": 197,
      "function": "bpf_opt_remove_dead_code"
    },
    {
      "file": "kernel/bpf/verifier.c:20089:20089",
      "inclusive_ns": 294,
      "exclusive_ns": 294,
      "function": "bpf_opt_remove_nops"
    },
    {
      "file": "kernel/bpf/verifier.c:20097:20097",
      "inclusive_ns": 410,
      "exclusive_ns": 410,
      "function": "bpf_convert_ctx_accesses"
    },
    {
      "file": "kernel/bpf/verifier.c:20100:20100",
      "inclusive_ns": 9700,
      "exclusive_ns": 9700,
      "function": "bpf_do_misc_fixups"
    },
    {
      "file": "kernel/bpf/verifier.c:20105:20105",
      "inclusive_ns": 151,
      "exclusive_ns": 151,
      "function": "bpf_prog_is_offloaded"
    },
    {
      "file": "kernel/bpf/verifier.c:20106:20106",
      "inclusive_ns": 306,
      "exclusive_ns": 306,
      "function": "bpf_opt_subreg_zext_lo32_rnd_hi"
    },
    {
      "file": "kernel/bpf/verifier.c:20112:20112",
      "inclusive_ns": 153,
      "exclusive_ns": 153,
      "function": "bpf_fixup_call_args"
    }
  ],
  "bpf_insns": [
    {
      "code": 183,
      "dst": 2,
      "src": 0,
      "off": 0,
      "imm": 0
    },
    {
      "code": 123,
      "dst": 10,
      "src": 2,
      "off": -8,
      "imm": 0
    },
    {
      "code": 113,
      "dst": 1,
      "src": 1,
      "off": 49,
      "imm": 0
    },
    {
      "code": 115,
      "dst": 10,
      "src": 1,
      "off": -9,
      "imm": 0
    },
    {
      "code": 191,
      "dst": 2,
      "src": 10,
      "off": 0,
      "imm": 0
    },
    {
      "code": 7,
      "dst": 2,
      "src": 0,
      "off": 0,
      "imm": -9
    },
    {
      "code": 24,
      "dst": 1,
      "src": 1,
      "off": 0,
      "imm": 5
    },
    {
      "code": 0,
      "dst": 0,
      "src": 0,
      "off": 0,
      "imm": 0
    },
    {
      "code": 133,
      "dst": 0,
      "src": 0,
      "off": 0,
      "imm": 1
    },
    {
      "code": 85,
      "dst": 0,
      "src": 0,
      "off": 14,
      "imm": 0
    },
    {
      "code": 191,
      "dst": 6,
      "src": 10,
      "off": 0,
      "imm": 0
    },
    {
      "code": 7,
      "dst": 6,
      "src": 0,
      "off": 0,
      "imm": -9
    },
    {
      "code": 191,
      "dst": 3,
      "src": 10,
      "off": 0,
      "imm": 0
    },
    {
      "code": 7,
      "dst": 3,
      "src": 0,
      "off": 0,
      "imm": -8
    },
    {
      "code": 24,
      "dst": 1,
      "src": 1,
      "off": 0,
      "imm": 5
    },
    {
      "code": 0,
      "dst": 0,
      "src": 0,
      "off": 0,
      "imm": 0
    },
    {
      "code": 191,
      "dst": 2,
      "src": 6,
      "off": 0,
      "imm": 0
    },
    {
      "code": 183,
      "dst": 4,
      "src": 0,
      "off": 0,
      "imm": 1
    },
    {
      "code": 133,
      "dst": 0,
      "src": 0,
      "off": 0,
      "imm": 2
    },
    {
      "code": 24,
      "dst": 1,
      "src": 1,
      "off": 0,
      "imm": 5
    },
    {
      "code": 0,
      "dst": 0,
      "src": 0,
      "off": 0,
      "imm": 0
    },
    {
      "code": 191,
      "dst": 2,
      "src": 6,
      "off": 0,
      "imm": 0
    },
    {
      "code": 133,
      "dst": 0,
      "src": 0,
      "off": 0,
      "imm": 1
    },
    {
      "code": 21,
      "dst": 0,
      "src": 0,
      "off": 3,
      "imm": 0
    },
    {
      "code": 121,
      "dst": 1,
      "src": 0,
      "off": 0,
      "imm": 0
    },
    {
      "code": 7,
      "dst": 1,
      "src": 0,
      "off": 0,
      "imm": 1
    },
    {
      "code": 123,
      "dst": 0,
      "src": 1,
      "off": 0,
      "imm": 0
    },
    {
      "code": 180,
      "dst": 0,
      "src": 0,
      "off": 0,
      "imm": 0
    },
    {
      "code": 149,
      "dst": 0,
      "src": 0,
      "off": 0,
      "imm": 0
    }
  ]
}