{"program_name":"selftest_tunnel_43","verification_ns":524599,"kernel_compiler":"clang","trace_record_count":140,"file_ids":{"0":"kernel/bpf/verifier.c","1":"kernel/bpf/liveness.c","2":"kernel/bpf/states.c"},"profile_stats":{"subprog_cnt":1,"insn_processed":48,"complexity_limit_insns":1000000,"max_states_per_insn":0,"total_states":3,"peak_states":3,"longest_mark_read_walk":0},"bpf_insns":[{"code":191,"dst":6,"src":1,"off":0,"imm":0},{"code":191,"dst":2,"src":10,"off":0,"imm":0},{"code":7,"dst":2,"src":0,"off":0,"imm":-44},{"code":180,"dst":3,"src":0,"off":0,"imm":44},{"code":183,"dst":4,"src":0,"off":0,"imm":1},{"code":133,"dst":0,"src":0,"off":0,"imm":20},{"code":102,"dst":0,"src":0,"off":8,"imm":-1},{"code":24,"dst":1,"src":2,"off":0,"imm":5},{"code":0,"dst":0,"src":0,"off":0,"imm":1272},{"code":180,"dst":2,"src":0,"off":0,"imm":22},{"code":180,"dst":3,"src":0,"off":0,"imm":697},{"code":188,"dst":4,"src":0,"off":0,"imm":0},{"code":133,"dst":0,"src":0,"off":0,"imm":6},{"code":180,"dst":0,"src":0,"off":0,"imm":2},{"code":5,"dst":0,"src":0,"off":22,"imm":0},{"code":191,"dst":2,"src":10,"off":0,"imm":0},{"code":7,"dst":2,"src":0,"off":0,"imm":-48},{"code":191,"dst":1,"src":6,"off":0,"imm":0},{"code":180,"dst":3,"src":0,"off":0,"imm":4},{"code":133,"dst":0,"src":0,"off":0,"imm":29},{"code":102,"dst":0,"src":0,"off":4,"imm":-1},{"code":191,"dst":1,"src":10,"off":0,"imm":0},{"code":7,"dst":1,"src":0,"off":0,"imm":-48},{"code":180,"dst":2,"src":0,"off":0,"imm":0},{"code":107,"dst":1,"src":2,"off":0,"imm":0},{"code":191,"dst":1,"src":10,"off":0,"imm":0},{"code":7,"dst":1,"src":0,"off":0,"imm":-44},{"code":191,"dst":2,"src":10,"off":0,"imm":0},{"code":7,"dst":2,"src":0,"off":0,"imm":-48},{"code":105,"dst":5,"src":2,"off":0,"imm":0},{"code":97,"dst":4,"src":1,"off":4,"imm":0},{"code":97,"dst":3,"src":1,"off":0,"imm":0},{"code":24,"dst":1,"src":2,"off":0,"imm":5},{"code":0,"dst":0,"src":0,"off":0,"imm":1294},{"code":180,"dst":2,"src":0,"off":0,"imm":41},{"code":133,"dst":0,"src":0,"off":0,"imm":6},{"code":180,"dst":0,"src":0,"off":0,"imm":0},{"code":149,"dst":0,"src":0,"off":0,"imm":0}],"call_tree":[{"f":"0:19997:19997","i":498,"e":498,"fn":"bpf_check_btf_info_early"},{"f":"0:20001:20001","i":3364,"e":3364,"fn":"add_subprog_and_kfunc"},{"f":"0:20005:20005","i":472,"e":472,"fn":"check_subprogs"},{"f":"0:20009:20009","i":1519,"e":1519,"fn":"bpf_check_btf_info"},{"f":"0:20013:20013","i":4377,"e":4377,"fn":"check_and_resolve_insns"},{"f":"0:20017:20017","i":77,"e":77,"fn":"bpf_prog_is_offloaded"},{"f":"0:20023:20023","i":72607,"e":72607,"fn":"bpf_check_cfg"},{"f":"0:20027:20027","i":1741,"e":1741,"fn":"bpf_compute_postorder"},{"f":"0:20031:20031","i":700,"e":700,"fn":"bpf_stack_liveness_init"},{"f":"0:20035:20035","i":87,"e":87,"fn":"check_attach_btf_id"},{"f":"0:20039:20039","i":5393,"e":5393,"fn":"bpf_compute_const_regs"},{"f":"0:20043:20043","i":288,"e":288,"fn":"bpf_prune_dead_branches"},{"f":"0:20047:20047","i":807,"e":807,"fn":"sort_subprogs_topo"},{"f":"0:20051:20051","i":3077,"e":3077,"fn":"bpf_compute_scc"},{"f":"0:20055:20055","i":205608,"e":205608,"fn":"bpf_compute_live_registers"},{"f":"0:20059:20059","i":18513,"e":18513,"fn":"mark_fastcall_patterns"},{"f":"0:20063:20063","i":119721,"e":3757,"fn":"do_check_main","c":[{"f":"0:18708:18798","i":3356,"e":3356},{"f":"0:18807:18807","i":112608,"e":12449,"fn":"do_check","c":[{"f":"0:17790:17790","i":379,"e":221,"fn":"do_check_insn","a":0,"c":[{"f":"0:17578:17578","i":158,"e":158,"fn":"check_alu_op"}]},{"f":"0:17790:17790","i":351,"e":211,"fn":"do_check_insn","a":1,"c":[{"f":"0:17578:17578","i":140,"e":140,"fn":"check_alu_op"}]},{"f":"0:17790:17790","i":537,"e":224,"fn":"do_check_insn","a":2,"c":[{"f":"0:17578:17578","i":313,"e":313,"fn":"check_alu_op"}]},{"f":"0:17790:17790","i":338,"e":211,"fn":"do_check_insn","a":3,"c":[{"f":"0:17578:17578","i":127,"e":127,"fn":"check_alu_op"}]},{"f":"0:17790:17790","i":330,"e":209,"fn":"do_check_insn","a":4,"c":[{"f":"0:17578:17578","i":121,"e":121,"fn":"check_alu_op"}]},{"f":"0:17790:17790","i":3486,"e":242,"fn":"do_check_insn","a":5,"c":[{"f":"0:17629:17629","i":3244,"e":3244,"fn":"check_helper_call"}]},{"f":"0:17703:17703","i":416,"e":416,"fn":"bpf_is_state_visited","a":6},{"f":"0:17790:17790","i":2072,"e":245,"fn":"do_check_insn","a":6,"c":[{"f":"0:17642:17642","i":1827,"e":1827,"fn":"check_cond_jmp_op"}]},{"f":"0:17790:17790","i":384,"e":251,"fn":"do_check_insn","a":8,"c":[{"f":"0:17651:17651","i":133,"e":133,"fn":"check_ld_imm"}]},{"f":"0:17790:17790","i":348,"e":210,"fn":"do_check_insn","a":9,"c":[{"f":"0:17578:17578","i":138,"e":138,"fn":"check_alu_op"}]},{"f":"0:17790:17790","i":308,"e":209,"fn":"do_check_insn","a":10,"c":[{"f":"0:17578:17578","i":99,"e":99,"fn":"check_alu_op"}]},{"f":"0:17790:17790","i":524,"e":211,"fn":"do_check_insn","a":11,"c":[{"f":"0:17578:17578","i":313,"e":313,"fn":"check_alu_op"}]},{"f":"0:17790:17790","i":18282,"e":17022,"fn":"do_check_insn","a":12,"c":[{"f":"0:17629:17629","i":1260,"e":1260,"fn":"check_helper_call"}]},{"f":"0:17703:17703","i":1843,"e":1843,"fn":"bpf_is_state_visited","a":13},{"f":"0:17790:17790","i":354,"e":214,"fn":"do_check_insn","a":13,"c":[{"f":"0:17578:17578","i":140,"e":140,"fn":"check_alu_op"}]},{"f":"0:17790:17790","i":109,"e":109,"fn":"do_check_insn","a":37},{"f":"0:17703:17703","i":327,"e":327,"fn":"bpf_is_state_visited","a":37},{"f":"0:17790:17790","i":344,"e":244,"fn":"do_check_insn","a":37,"c":[{"f":"0:17640:17640","i":100,"e":100,"fn":"process_bpf_exit_full"}]},{"f":"0:17703:17703","i":276,"e":276,"fn":"bpf_is_state_visited","a":15},{"f":"0:17790:17790","i":329,"e":211,"fn":"do_check_insn","a":15,"c":[{"f":"0:17578:17578","i":118,"e":118,"fn":"check_alu_op"}]},{"f":"0:17790:17790","i":510,"e":211,"fn":"do_check_insn","a":16,"c":[{"f":"0:17578:17578","i":299,"e":299,"fn":"check_alu_op"}]},{"f":"0:17790:17790","i":359,"e":212,"fn":"do_check_insn","a":17,"c":[{"f":"0:17578:17578","i":147,"e":147,"fn":"check_alu_op"}]},{"f":"0:17790:17790","i":330,"e":210,"fn":"do_check_insn","a":18,"c":[{"f":"0:17578:17578","i":120,"e":120,"fn":"check_alu_op"}]},{"f":"0:17790:17790","i":1014,"e":241,"fn":"do_check_insn","a":19,"c":[{"f":"0:17629:17629","i":773,"e":773,"fn":"check_helper_call"}]},{"f":"0:17703:17703","i":1521,"e":1521,"fn":"bpf_is_state_visited","a":20},{"f":"0:17790:17790","i":2288,"e":246,"fn":"do_check_insn","a":20,"c":[{"f":"0:17642:17642","i":2042,"e":2042,"fn":"check_cond_jmp_op"}]},{"f":"0:17790:17790","i":362,"e":216,"fn":"do_check_insn","a":21,"c":[{"f":"0:17578:17578","i":146,"e":146,"fn":"check_alu_op"}]},{"f":"0:17790:17790","i":504,"e":212,"fn":"do_check_insn","a":22,"c":[{"f":"0:17578:17578","i":292,"e":292,"fn":"check_alu_op"}]},{"f":"0:17790:17790","i":349,"e":209,"fn":"do_check_insn","a":23,"c":[{"f":"0:17578:17578","i":140,"e":140,"fn":"check_alu_op"}]},{"f":"0:17790:17790","i":886,"e":270,"fn":"do_check_insn","a":24,"c":[{"f":"0:17588:17588","i":616,"e":616,"fn":"check_store_reg"}]},{"f":"0:17703:17703","i":369,"e":369,"fn":"bpf_is_state_visited","a":25},{"f":"0:17790:17790","i":385,"e":240,"fn":"do_check_insn","a":25,"c":[{"f":"0:17578:17578","i":145,"e":145,"fn":"check_alu_op"}]},{"f":"0:17790:17790","i":507,"e":215,"fn":"do_check_insn","a":26,"c":[{"f":"0:17578:17578","i":292,"e":292,"fn":"check_alu_op"}]},{"f":"0:17790:17790","i":349,"e":215,"fn":"do_check_insn","a":27,"c":[{"f":"0:17578:17578","i":134,"e":134,"fn":"check_alu_op"}]},{"f":"0:17790:17790","i":491,"e":215,"fn":"do_check_insn","a":28,"c":[{"f":"0:17578:17578","i":276,"e":276,"fn":"check_alu_op"}]},{"f":"0:17790:17790","i":833,"e":238,"fn":"do_check_insn","a":29,"c":[{"f":"0:17583:17583","i":595,"e":595,"fn":"check_load_mem"}]},{"f":"0:17790:17790","i":510,"e":218,"fn":"do_check_insn","a":30,"c":[{"f":"0:17583:17583","i":292,"e":292,"fn":"check_load_mem"}]},{"f":"0:17790:17790","i":492,"e":213,"fn":"do_check_insn","a":31,"c":[{"f":"0:17583:17583","i":279,"e":279,"fn":"check_load_mem"}]},{"f":"0:17790:17790","i":364,"e":242,"fn":"do_check_insn","a":33,"c":[{"f":"0:17651:17651","i":122,"e":122,"fn":"check_ld_imm"}]},{"f":"0:17790:17790","i":317,"e":218,"fn":"do_check_insn","a":34,"c":[{"f":"0:17578:17578","i":99,"e":99,"fn":"check_alu_op"}]},{"f":"0:17790:17790","i":28544,"e":282,"fn":"do_check_insn","a":35,"c":[{"f":"0:17629:17629","i":28262,"e":28262,"fn":"check_helper_call"}]},{"f":"0:17703:17703","i":2370,"e":2370,"fn":"bpf_is_state_visited","a":36},{"f":"0:17790:17790","i":367,"e":227,"fn":"do_check_insn","a":36,"c":[{"f":"0:17578:17578","i":140,"e":140,"fn":"check_alu_op"}]},{"f":"0:17703:17703","i":307,"e":307,"fn":"bpf_is_state_visited","a":37},{"f":"0:17790:17790","i":340,"e":243,"fn":"do_check_insn","a":37,"c":[{"f":"0:17640:17640","i":97,"e":97,"fn":"process_bpf_exit_full"}]},{"f":"0:17703:17703","i":338,"e":338,"fn":"bpf_is_state_visited","a":25},{"f":"0:17790:17790","i":323,"e":210,"fn":"do_check_insn","a":25,"c":[{"f":"0:17578:17578","i":113,"e":113,"fn":"check_alu_op"}]},{"f":"0:17790:17790","i":520,"e":214,"fn":"do_check_insn","a":26,"c":[{"f":"0:17578:17578","i":306,"e":306,"fn":"check_alu_op"}]},{"f":"0:17790:17790","i":361,"e":216,"fn":"do_check_insn","a":27,"c":[{"f":"0:17578:17578","i":145,"e":145,"fn":"check_alu_op"}]},{"f":"0:17790:17790","i":486,"e":210,"fn":"do_check_insn","a":28,"c":[{"f":"0:17578:17578","i":276,"e":276,"fn":"check_alu_op"}]},{"f":"0:17790:17790","i":620,"e":235,"fn":"do_check_insn","a":29,"c":[{"f":"0:17583:17583","i":385,"e":385,"fn":"check_load_mem"}]},{"f":"0:17790:17790","i":521,"e":212,"fn":"do_check_insn","a":30,"c":[{"f":"0:17583:17583","i":309,"e":309,"fn":"check_load_mem"}]},{"f":"0:17790:17790","i":502,"e":209,"fn":"do_check_insn","a":31,"c":[{"f":"0:17583:17583","i":293,"e":293,"fn":"check_load_mem"}]},{"f":"0:17790:17790","i":367,"e":236,"fn":"do_check_insn","a":33,"c":[{"f":"0:17651:17651","i":131,"e":131,"fn":"check_ld_imm"}]},{"f":"0:17790:17790","i":350,"e":213,"fn":"do_check_insn","a":34,"c":[{"f":"0:17578:17578","i":137,"e":137,"fn":"check_alu_op"}]},{"f":"0:17790:17790","i":17972,"e":16698,"fn":"do_check_insn","a":35,"c":[{"f":"0:17629:17629","i":1274,"e":1274,"fn":"check_helper_call"}]},{"f":"0:17703:17703","i":1794,"e":1049,"fn":"bpf_is_state_visited","a":36,"c":[{"f":"2:1370:1370","i":450,"e":371,"fn":"states_equal","a":36,"c":[{"f":"2:967:967","i":79,"e":79,"fn":"refsafe"}]},{"f":"2:1382:1382","i":295,"e":295,"fn":"propagate_precision","a":36}]}]}]},{"f":"0:20064:20064","i":89,"e":89,"fn":"do_check_subprogs"},{"f":"0:20066:20066","i":82,"e":82,"fn":"bpf_prog_is_offloaded"},{"f":"0:20076:20076","i":192,"e":192,"fn":"bpf_remove_fastcall_spills_fills"},{"f":"0:20079:20079","i":599,"e":599,"fn":"check_max_stack_depth"},{"f":"0:20083:20083","i":308,"e":308,"fn":"bpf_optimize_bpf_loop"},{"f":"0:20087:20087","i":191,"e":191,"fn":"bpf_opt_hard_wire_dead_code_branches"},{"f":"0:20089:20089","i":152,"e":152,"fn":"bpf_opt_remove_dead_code"},{"f":"0:20091:20091","i":174,"e":174,"fn":"bpf_opt_remove_nops"},{"f":"0:20099:20099","i":464,"e":464,"fn":"bpf_convert_ctx_accesses"},{"f":"0:20102:20102","i":19303,"e":19303,"fn":"bpf_do_misc_fixups"},{"f":"0:20107:20107","i":95,"e":95,"fn":"bpf_prog_is_offloaded"},{"f":"0:20108:20108","i":443,"e":443,"fn":"bpf_opt_subreg_zext_lo32_rnd_hi32"},{"f":"0:20114:20114","i":82,"e":82,"fn":"bpf_fixup_call_args"}]}