{"program_name":"selftest_reg_bounds_rand_consts_u64_s64_905","verification_ns":252796,"kernel_compiler":"clang","trace_record_count":99,"file_ids":{"0":"kernel/bpf/verifier.c","1":"kernel/bpf/liveness.c","2":"kernel/bpf/states.c"},"profile_stats":{"subprog_cnt":1,"insn_processed":26,"complexity_limit_insns":1000000,"max_states_per_insn":0,"total_states":3,"peak_states":3,"longest_mark_read_walk":0},"bpf_insns":[{"code":5,"dst":0,"src":0,"off":2,"imm":0},{"code":183,"dst":0,"src":0,"off":0,"imm":0},{"code":149,"dst":0,"src":0,"off":0,"imm":0},{"code":133,"dst":0,"src":0,"off":0,"imm":14},{"code":191,"dst":6,"src":0,"off":0,"imm":0},{"code":133,"dst":0,"src":0,"off":0,"imm":14},{"code":191,"dst":7,"src":0,"off":0,"imm":0},{"code":24,"dst":1,"src":0,"off":0,"imm":184464817},{"code":0,"dst":0,"src":0,"off":0,"imm":-839156199},{"code":24,"dst":2,"src":0,"off":0,"imm":-248105305},{"code":0,"dst":0,"src":0,"off":0,"imm":-48870004},{"code":173,"dst":6,"src":1,"off":-11,"imm":0},{"code":45,"dst":6,"src":2,"off":-12,"imm":0},{"code":24,"dst":1,"src":0,"off":0,"imm":1513950769},{"code":0,"dst":0,"src":0,"off":0,"imm":-1948066335},{"code":24,"dst":2,"src":0,"off":0,"imm":1513950769},{"code":0,"dst":0,"src":0,"off":0,"imm":-1948066335},{"code":173,"dst":7,"src":1,"off":-17,"imm":0},{"code":45,"dst":7,"src":2,"off":-18,"imm":0},{"code":191,"dst":0,"src":6,"off":0,"imm":0},{"code":191,"dst":0,"src":7,"off":0,"imm":0},{"code":109,"dst":6,"src":7,"off":3,"imm":0},{"code":191,"dst":0,"src":6,"off":0,"imm":0},{"code":191,"dst":0,"src":7,"off":0,"imm":0},{"code":133,"dst":0,"src":0,"off":0,"imm":57005},{"code":191,"dst":0,"src":6,"off":0,"imm":0},{"code":191,"dst":0,"src":7,"off":0,"imm":0},{"code":149,"dst":0,"src":0,"off":0,"imm":0}],"call_tree":[{"f":"0:19997:19997","i":84,"e":84,"fn":"bpf_check_btf_info_early"},{"f":"0:20001:20001","i":401,"e":401,"fn":"add_subprog_and_kfunc"},{"f":"0:20005:20005","i":223,"e":223,"fn":"check_subprogs"},{"f":"0:20009:20009","i":82,"e":82,"fn":"bpf_check_btf_info"},{"f":"0:20013:20013","i":2336,"e":2336,"fn":"check_and_resolve_insns"},{"f":"0:20017:20017","i":83,"e":83,"fn":"bpf_prog_is_offloaded"},{"f":"0:20023:20023","i":1521,"e":1521,"fn":"bpf_check_cfg"},{"f":"0:20027:20027","i":1141,"e":1141,"fn":"bpf_compute_postorder"},{"f":"0:20031:20031","i":576,"e":576,"fn":"bpf_stack_liveness_init"},{"f":"0:20035:20035","i":90,"e":90,"fn":"check_attach_btf_id"},{"f":"0:20039:20039","i":3119,"e":3119,"fn":"bpf_compute_const_regs"},{"f":"0:20043:20043","i":238,"e":238,"fn":"bpf_prune_dead_branches"},{"f":"0:20047:20047","i":918,"e":918,"fn":"sort_subprogs_topo"},{"f":"0:20051:20051","i":2001,"e":2001,"fn":"bpf_compute_scc"},{"f":"0:20055:20055","i":109420,"e":109420,"fn":"bpf_compute_live_registers"},{"f":"0:20059:20059","i":227,"e":227,"fn":"mark_fastcall_patterns"},{"f":"0:20063:20063","i":113898,"e":2816,"fn":"do_check_main","c":[{"f":"0:18708:18798","i":83,"e":83},{"f":"0:18807:18807","i":110999,"e":45045,"fn":"do_check","c":[{"f":"0:17790:17790","i":90,"e":90,"fn":"do_check_insn","a":3},{"f":"0:17703:17703","i":158,"e":158,"fn":"bpf_is_state_visited","a":3},{"f":"0:17790:17790","i":481,"e":222,"fn":"do_check_insn","a":3,"c":[{"f":"0:17629:17629","i":259,"e":259,"fn":"check_helper_call"}]},{"f":"0:17703:17703","i":206,"e":206,"fn":"bpf_is_state_visited","a":4},{"f":"0:17790:17790","i":344,"e":222,"fn":"do_check_insn","a":4,"c":[{"f":"0:17578:17578","i":122,"e":122,"fn":"check_alu_op"}]},{"f":"0:17790:17790","i":481,"e":226,"fn":"do_check_insn","a":5,"c":[{"f":"0:17629:17629","i":255,"e":255,"fn":"check_helper_call"}]},{"f":"0:17703:17703","i":147,"e":147,"fn":"bpf_is_state_visited","a":6},{"f":"0:17790:17790","i":330,"e":211,"fn":"do_check_insn","a":6,"c":[{"f":"0:17578:17578","i":119,"e":119,"fn":"check_alu_op"}]},{"f":"0:17790:17790","i":299,"e":211,"fn":"do_check_insn","a":8,"c":[{"f":"0:17651:17651","i":88,"e":88,"fn":"check_ld_imm"}]},{"f":"0:17790:17790","i":338,"e":210,"fn":"do_check_insn","a":10,"c":[{"f":"0:17651:17651","i":128,"e":128,"fn":"check_ld_imm"}]},{"f":"0:17703:17703","i":1024,"e":1024,"fn":"bpf_is_state_visited","a":11},{"f":"0:17790:17790","i":3945,"e":235,"fn":"do_check_insn","a":11,"c":[{"f":"0:17642:17642","i":3710,"e":3710,"fn":"check_cond_jmp_op"}]},{"f":"0:17703:17703","i":167,"e":167,"fn":"bpf_is_state_visited","a":12},{"f":"0:17790:17790","i":3905,"e":231,"fn":"do_check_insn","a":12,"c":[{"f":"0:17642:17642","i":3674,"e":3674,"fn":"check_cond_jmp_op"}]},{"f":"0:17790:17790","i":308,"e":217,"fn":"do_check_insn","a":14,"c":[{"f":"0:17651:17651","i":91,"e":91,"fn":"check_ld_imm"}]},{"f":"0:17790:17790","i":305,"e":214,"fn":"do_check_insn","a":16,"c":[{"f":"0:17651:17651","i":91,"e":91,"fn":"check_ld_imm"}]},{"f":"0:17703:17703","i":123,"e":123,"fn":"bpf_is_state_visited","a":17},{"f":"0:17790:17790","i":3844,"e":231,"fn":"do_check_insn","a":17,"c":[{"f":"0:17642:17642","i":3613,"e":3613,"fn":"check_cond_jmp_op"}]},{"f":"0:17703:17703","i":148,"e":148,"fn":"bpf_is_state_visited","a":18},{"f":"0:17790:17790","i":2339,"e":219,"fn":"do_check_insn","a":18,"c":[{"f":"0:17642:17642","i":2120,"e":2120,"fn":"check_cond_jmp_op"}]},{"f":"0:17790:17790","i":333,"e":214,"fn":"do_check_insn","a":19,"c":[{"f":"0:17578:17578","i":119,"e":119,"fn":"check_alu_op"}]},{"f":"0:17790:17790","i":359,"e":222,"fn":"do_check_insn","a":20,"c":[{"f":"0:17578:17578","i":137,"e":137,"fn":"check_alu_op"}]},{"f":"0:17703:17703","i":898,"e":898,"fn":"bpf_is_state_visited","a":21},{"f":"0:17790:17790","i":39996,"e":243,"fn":"do_check_insn","a":24,"c":[{"f":"0:17642:17642","i":39753,"e":39753,"fn":"check_cond_jmp_op"}]},{"f":"0:17703:17703","i":179,"e":179,"fn":"bpf_is_state_visited","a":25},{"f":"0:17790:17790","i":333,"e":214,"fn":"do_check_insn","a":25,"c":[{"f":"0:17578:17578","i":119,"e":119,"fn":"check_alu_op"}]},{"f":"0:17790:17790","i":352,"e":214,"fn":"do_check_insn","a":26,"c":[{"f":"0:17578:17578","i":138,"e":138,"fn":"check_alu_op"}]},{"f":"0:17790:17790","i":320,"e":218,"fn":"do_check_insn","a":27,"c":[{"f":"0:17640:17640","i":102,"e":102,"fn":"process_bpf_exit_full"}]},{"f":"0:17703:17703","i":185,"e":185,"fn":"bpf_is_state_visited","a":1},{"f":"0:17790:17790","i":357,"e":216,"fn":"do_check_insn","a":1,"c":[{"f":"0:17578:17578","i":141,"e":141,"fn":"check_alu_op"}]},{"f":"0:17790:17790","i":319,"e":219,"fn":"do_check_insn","a":2,"c":[{"f":"0:17640:17640","i":100,"e":100,"fn":"process_bpf_exit_full"}]},{"f":"0:17703:17703","i":149,"e":149,"fn":"bpf_is_state_visited","a":1},{"f":"0:17790:17790","i":319,"e":214,"fn":"do_check_insn","a":1,"c":[{"f":"0:17578:17578","i":105,"e":105,"fn":"check_alu_op"}]},{"f":"0:17790:17790","i":319,"e":218,"fn":"do_check_insn","a":2,"c":[{"f":"0:17640:17640","i":101,"e":101,"fn":"process_bpf_exit_full"}]},{"f":"0:17703:17703","i":990,"e":990,"fn":"bpf_is_state_visited","a":1},{"f":"0:17790:17790","i":356,"e":217,"fn":"do_check_insn","a":1,"c":[{"f":"0:17578:17578","i":139,"e":139,"fn":"check_alu_op"}]},{"f":"0:17790:17790","i":314,"e":215,"fn":"do_check_insn","a":2,"c":[{"f":"0:17640:17640","i":99,"e":99,"fn":"process_bpf_exit_full"}]},{"f":"0:17703:17703","i":894,"e":480,"fn":"bpf_is_state_visited","a":1,"c":[{"f":"2:1370:1370","i":312,"e":230,"fn":"states_equal","a":1,"c":[{"f":"2:967:967","i":82,"e":82,"fn":"refsafe"}]},{"f":"2:1382:1382","i":102,"e":102,"fn":"propagate_precision","a":1}]}]}]},{"f":"0:20064:20064","i":80,"e":80,"fn":"do_check_subprogs"},{"f":"0:20066:20066","i":84,"e":84,"fn":"bpf_prog_is_offloaded"},{"f":"0:20076:20076","i":145,"e":145,"fn":"bpf_remove_fastcall_spills_fills"},{"f":"0:20079:20079","i":476,"e":476,"fn":"check_max_stack_depth"},{"f":"0:20083:20083","i":155,"e":155,"fn":"bpf_optimize_bpf_loop"},{"f":"0:20087:20087","i":167,"e":167,"fn":"bpf_opt_hard_wire_dead_code_branches"},{"f":"0:20089:20089","i":320,"e":320,"fn":"bpf_opt_remove_dead_code"},{"f":"0:20091:20091","i":282,"e":282,"fn":"bpf_opt_remove_nops"},{"f":"0:20099:20099","i":160,"e":160,"fn":"bpf_convert_ctx_accesses"},{"f":"0:20102:20102","i":633,"e":633,"fn":"bpf_do_misc_fixups"},{"f":"0:20107:20107","i":78,"e":78,"fn":"bpf_prog_is_offloaded"},{"f":"0:20108:20108","i":153,"e":153,"fn":"bpf_opt_subreg_zext_lo32_rnd_hi32"},{"f":"0:20114:20114","i":78,"e":78,"fn":"bpf_fixup_call_args"}]}