{"program_name":"selftest_connect_force_port_6","verification_ns":179757,"kernel_compiler":"clang","trace_record_count":106,"file_ids":{"0":"kernel/bpf/verifier.c","1":"kernel/bpf/liveness.c","2":"kernel/bpf/states.c"},"profile_stats":{"subprog_cnt":1,"insn_processed":31,"complexity_limit_insns":1000000,"max_states_per_insn":0,"total_states":2,"peak_states":2,"longest_mark_read_walk":0},"bpf_insns":[{"code":191,"dst":6,"src":1,"off":0,"imm":0},{"code":191,"dst":4,"src":10,"off":0,"imm":0},{"code":7,"dst":4,"src":0,"off":0,"imm":-4},{"code":180,"dst":2,"src":0,"off":0,"imm":1},{"code":180,"dst":3,"src":0,"off":0,"imm":12},{"code":180,"dst":5,"src":0,"off":0,"imm":4},{"code":133,"dst":0,"src":0,"off":0,"imm":57},{"code":21,"dst":0,"src":0,"off":2,"imm":0},{"code":180,"dst":0,"src":0,"off":0,"imm":1},{"code":149,"dst":0,"src":0,"off":0,"imm":0},{"code":191,"dst":4,"src":10,"off":0,"imm":0},{"code":7,"dst":4,"src":0,"off":0,"imm":-4},{"code":191,"dst":1,"src":6,"off":0,"imm":0},{"code":180,"dst":2,"src":0,"off":0,"imm":1},{"code":180,"dst":3,"src":0,"off":0,"imm":12},{"code":180,"dst":5,"src":0,"off":0,"imm":4},{"code":133,"dst":0,"src":0,"off":0,"imm":49},{"code":85,"dst":0,"src":0,"off":-10,"imm":0},{"code":97,"dst":1,"src":6,"off":24,"imm":0},{"code":24,"dst":2,"src":2,"off":0,"imm":8},{"code":0,"dst":0,"src":0,"off":0,"imm":0},{"code":105,"dst":2,"src":2,"off":0,"imm":0},{"code":220,"dst":2,"src":0,"off":0,"imm":16},{"code":94,"dst":1,"src":2,"off":-16,"imm":0},{"code":180,"dst":1,"src":0,"off":0,"imm":24810},{"code":99,"dst":6,"src":1,"off":24,"imm":0},{"code":180,"dst":1,"src":0,"off":0,"imm":67305985},{"code":99,"dst":6,"src":1,"off":4,"imm":0},{"code":5,"dst":0,"src":0,"off":-21,"imm":0}],"call_tree":[{"f":"0:19997:19997","i":510,"e":510,"fn":"bpf_check_btf_info_early"},{"f":"0:20001:20001","i":465,"e":465,"fn":"add_subprog_and_kfunc"},{"f":"0:20005:20005","i":463,"e":463,"fn":"check_subprogs"},{"f":"0:20009:20009","i":1432,"e":1432,"fn":"bpf_check_btf_info"},{"f":"0:20013:20013","i":4021,"e":4021,"fn":"check_and_resolve_insns"},{"f":"0:20017:20017","i":77,"e":77,"fn":"bpf_prog_is_offloaded"},{"f":"0:20023:20023","i":2593,"e":2593,"fn":"bpf_check_cfg"},{"f":"0:20027:20027","i":1760,"e":1760,"fn":"bpf_compute_postorder"},{"f":"0:20031:20031","i":602,"e":602,"fn":"bpf_stack_liveness_init"},{"f":"0:20035:20035","i":83,"e":83,"fn":"check_attach_btf_id"},{"f":"0:20039:20039","i":5804,"e":5804,"fn":"bpf_compute_const_regs"},{"f":"0:20043:20043","i":402,"e":402,"fn":"bpf_prune_dead_branches"},{"f":"0:20047:20047","i":1134,"e":1134,"fn":"sort_subprogs_topo"},{"f":"0:20051:20051","i":3126,"e":3126,"fn":"bpf_compute_scc"},{"f":"0:20055:20055","i":85086,"e":85086,"fn":"bpf_compute_live_registers"},{"f":"0:20059:20059","i":287,"e":287,"fn":"mark_fastcall_patterns"},{"f":"0:20063:20063","i":41379,"e":2977,"fn":"do_check_main","c":[{"f":"0:18708:18798","i":520,"e":520},{"f":"0:18807:18807","i":37882,"e":9221,"fn":"do_check","c":[{"f":"0:17790:17790","i":423,"e":261,"fn":"do_check_insn","a":0,"c":[{"f":"0:17578:17578","i":162,"e":162,"fn":"check_alu_op"}]},{"f":"0:17790:17790","i":404,"e":238,"fn":"do_check_insn","a":1,"c":[{"f":"0:17578:17578","i":166,"e":166,"fn":"check_alu_op"}]},{"f":"0:17790:17790","i":783,"e":222,"fn":"do_check_insn","a":2,"c":[{"f":"0:17578:17578","i":561,"e":561,"fn":"check_alu_op"}]},{"f":"0:17790:17790","i":330,"e":209,"fn":"do_check_insn","a":3,"c":[{"f":"0:17578:17578","i":121,"e":121,"fn":"check_alu_op"}]},{"f":"0:17790:17790","i":340,"e":217,"fn":"do_check_insn","a":4,"c":[{"f":"0:17578:17578","i":123,"e":123,"fn":"check_alu_op"}]},{"f":"0:17790:17790","i":348,"e":216,"fn":"do_check_insn","a":5,"c":[{"f":"0:17578:17578","i":132,"e":132,"fn":"check_alu_op"}]},{"f":"0:17790:17790","i":2336,"e":270,"fn":"do_check_insn","a":6,"c":[{"f":"0:17629:17629","i":2066,"e":2066,"fn":"check_helper_call"}]},{"f":"0:17703:17703","i":327,"e":327,"fn":"bpf_is_state_visited","a":7},{"f":"0:17790:17790","i":2642,"e":248,"fn":"do_check_insn","a":7,"c":[{"f":"0:17642:17642","i":2394,"e":2394,"fn":"check_cond_jmp_op"}]},{"f":"0:17703:17703","i":1651,"e":1651,"fn":"bpf_is_state_visited","a":8},{"f":"0:17790:17790","i":353,"e":244,"fn":"do_check_insn","a":8,"c":[{"f":"0:17578:17578","i":109,"e":109,"fn":"check_alu_op"}]},{"f":"0:17790:17790","i":593,"e":242,"fn":"do_check_insn","a":9,"c":[{"f":"0:17640:17640","i":351,"e":351,"fn":"process_bpf_exit_full"}]},{"f":"0:17703:17703","i":261,"e":261,"fn":"bpf_is_state_visited","a":10},{"f":"0:17790:17790","i":397,"e":237,"fn":"do_check_insn","a":10,"c":[{"f":"0:17578:17578","i":160,"e":160,"fn":"check_alu_op"}]},{"f":"0:17790:17790","i":543,"e":236,"fn":"do_check_insn","a":11,"c":[{"f":"0:17578:17578","i":307,"e":307,"fn":"check_alu_op"}]},{"f":"0:17790:17790","i":372,"e":210,"fn":"do_check_insn","a":12,"c":[{"f":"0:17578:17578","i":162,"e":162,"fn":"check_alu_op"}]},{"f":"0:17790:17790","i":350,"e":215,"fn":"do_check_insn","a":13,"c":[{"f":"0:17578:17578","i":135,"e":135,"fn":"check_alu_op"}]},{"f":"0:17790:17790","i":312,"e":215,"fn":"do_check_insn","a":14,"c":[{"f":"0:17578:17578","i":97,"e":97,"fn":"check_alu_op"}]},{"f":"0:17790:17790","i":315,"e":217,"fn":"do_check_insn","a":15,"c":[{"f":"0:17578:17578","i":98,"e":98,"fn":"check_alu_op"}]},{"f":"0:17790:17790","i":976,"e":217,"fn":"do_check_insn","a":16,"c":[{"f":"0:17629:17629","i":759,"e":759,"fn":"check_helper_call"}]},{"f":"0:17703:17703","i":1673,"e":1673,"fn":"bpf_is_state_visited","a":17},{"f":"0:17790:17790","i":2407,"e":218,"fn":"do_check_insn","a":17,"c":[{"f":"0:17642:17642","i":2189,"e":2189,"fn":"check_cond_jmp_op"}]},{"f":"0:17790:17790","i":723,"e":253,"fn":"do_check_insn","a":18,"c":[{"f":"0:17583:17583","i":470,"e":470,"fn":"check_load_mem"}]},{"f":"0:17790:17790","i":448,"e":255,"fn":"do_check_insn","a":20,"c":[{"f":"0:17651:17651","i":193,"e":193,"fn":"check_ld_imm"}]},{"f":"0:17790:17790","i":635,"e":250,"fn":"do_check_insn","a":21,"c":[{"f":"0:17583:17583","i":385,"e":385,"fn":"check_load_mem"}]},{"f":"0:17790:17790","i":676,"e":208,"fn":"do_check_insn","a":22,"c":[{"f":"0:17578:17578","i":468,"e":468,"fn":"check_alu_op"}]},{"f":"0:17703:17703","i":275,"e":275,"fn":"bpf_is_state_visited","a":23},{"f":"0:17790:17790","i":2476,"e":280,"fn":"do_check_insn","a":23,"c":[{"f":"0:17642:17642","i":2196,"e":2196,"fn":"check_cond_jmp_op"}]},{"f":"0:17790:17790","i":369,"e":236,"fn":"do_check_insn","a":24,"c":[{"f":"0:17578:17578","i":133,"e":133,"fn":"check_alu_op"}]},{"f":"0:17790:17790","i":510,"e":210,"fn":"do_check_insn","a":25,"c":[{"f":"0:17588:17588","i":300,"e":300,"fn":"check_store_reg"}]},{"f":"0:17790:17790","i":313,"e":209,"fn":"do_check_insn","a":26,"c":[{"f":"0:17578:17578","i":104,"e":104,"fn":"check_alu_op"}]},{"f":"0:17790:17790","i":423,"e":209,"fn":"do_check_insn","a":27,"c":[{"f":"0:17588:17588","i":214,"e":214,"fn":"check_store_reg"}]},{"f":"0:17790:17790","i":157,"e":157,"fn":"do_check_insn","a":8},{"f":"0:17703:17703","i":1582,"e":896,"fn":"bpf_is_state_visited","a":8,"c":[{"f":"2:1370:1370","i":438,"e":335,"fn":"states_equal","a":8,"c":[{"f":"2:967:967","i":103,"e":103,"fn":"refsafe"}]},{"f":"2:1382:1382","i":248,"e":248,"fn":"propagate_precision","a":8}]},{"f":"0:17703:17703","i":987,"e":487,"fn":"bpf_is_state_visited","a":8,"c":[{"f":"2:1370:1370","i":373,"e":293,"fn":"states_equal","a":8,"c":[{"f":"2:967:967","i":80,"e":80,"fn":"refsafe"}]},{"f":"2:1382:1382","i":127,"e":127,"fn":"propagate_precision","a":8}]},{"f":"0:17703:17703","i":951,"e":498,"fn":"bpf_is_state_visited","a":8,"c":[{"f":"2:1370:1370","i":354,"e":273,"fn":"states_equal","a":8,"c":[{"f":"2:967:967","i":81,"e":81,"fn":"refsafe"}]},{"f":"2:1382:1382","i":99,"e":99,"fn":"propagate_precision","a":8}]}]}]},{"f":"0:20064:20064","i":129,"e":129,"fn":"do_check_subprogs"},{"f":"0:20066:20066","i":75,"e":75,"fn":"bpf_prog_is_offloaded"},{"f":"0:20076:20076","i":195,"e":195,"fn":"bpf_remove_fastcall_spills_fills"},{"f":"0:20079:20079","i":528,"e":528,"fn":"check_max_stack_depth"},{"f":"0:20083:20083","i":212,"e":212,"fn":"bpf_optimize_bpf_loop"},{"f":"0:20087:20087","i":311,"e":311,"fn":"bpf_opt_hard_wire_dead_code_branches"},{"f":"0:20089:20089","i":128,"e":128,"fn":"bpf_opt_remove_dead_code"},{"f":"0:20091:20091","i":174,"e":174,"fn":"bpf_opt_remove_nops"},{"f":"0:20099:20099","i":6813,"e":6813,"fn":"bpf_convert_ctx_accesses"},{"f":"0:20102:20102","i":1249,"e":1249,"fn":"bpf_do_misc_fixups"},{"f":"0:20107:20107","i":76,"e":76,"fn":"bpf_prog_is_offloaded"},{"f":"0:20108:20108","i":593,"e":593,"fn":"bpf_opt_subreg_zext_lo32_rnd_hi32"},{"f":"0:20114:20114","i":76,"e":76,"fn":"bpf_fixup_call_args"}]}